{
  "title": "Yosuga no Sora",
  "altTitles": [
    "Yosuga no Sora: In Solitude, Where We Are Least Alone"
  ],
  "description": "After the sudden death of their parents, twin siblings Haruka and Sora Kasugano return to the quiet rural town where they spent much of their childhood. Hoping to start a new life while living in their late grandfather’s house, Haruka reconnects with old friends and classmates while trying to care for his fragile and emotionally dependent sister. However, as memories of the past slowly resurface, the relationships between the characters begin growing increasingly complicated and emotionally intense.\n\nAs Haruka becomes closer to several girls in the town, each relationship explores different emotions, personal struggles, and romantic tensions that gradually blur the boundaries between friendship, love, and loneliness. Combining romance, drama, and emotional storytelling, Yosuga no Sora presents a controversial yet deeply personal story about human connection, desire, grief, and the search for emotional comfort.",
  "type": "TV",
  "status": "Completed",
  "releaseYear": 2010,
  "genres": [
    "Romance",
    "Drama",
    "Slice of Life"
  ],
  "rating": 6.8,
  "studio": "feel.",
  "poster": "poster.jpg",
  "banner": "banner.jpg"
}